scrapework/__init__.py
scrapework/cache.py
scrapework/core/__init__.py
scrapework/core/collector.py
scrapework/core/context.py
scrapework/core/http_client.py
scrapework/core/logger.py
scrapework/handlers.py
scrapework/items.py
scrapework/middleware.py
scrapework/module.py
scrapework/monitors.py
scrapework/observer.py
scrapework/parsers.py
scrapework/processors.py
scrapework/reporter.py
scrapework/request.py
scrapework/scraper.py
scrapework-0.5.5.dist-info/METADATA
scrapework-0.5.5.dist-info/WHEEL
scrapework-0.5.5.dist-info/RECORD
