Metadata-Version: 2.1
Name: scrapework
Version: 0.5.5
Summary: simple scraping framework
Home-page: https://github.com/sbusso/scrapework
License: MIT
Author: Stéphane Busso
Author-email: stephane.busso@gmail.com
Requires-Python: >=3.11,<4.0
Classifier: License :: OSI Approved :: MIT License
Classifier: Programming Language :: Python :: 3
Classifier: Programming Language :: Python :: 3.11
Classifier: Programming Language :: Python :: 3.12
Requires-Dist: boto3 (>=1.34.68,<2.0.0)
Requires-Dist: courlan (>=1.0.0,<2.0.0)
Requires-Dist: fake-useragent (>=1.5.1,<2.0.0)
Requires-Dist: hishel (>=0.0.24,<0.0.27)
Requires-Dist: httpx (>=0.27.0,<0.28.0)
Requires-Dist: parsel (>=1.9.0,<2.0.0)
Requires-Dist: playwright (>=1.43.0,<2.0.0)
Requires-Dist: pydantic (>=2.6.4,<3.0.0)
Requires-Dist: python-dotenv (>=1.0.1,<2.0.0)
Requires-Dist: requests (>=2.31.0,<3.0.0)
Requires-Dist: rich (>=13.7.1,<14.0.0)
Requires-Dist: trafilatura (>=1.8.0,<2.0.0)
Project-URL: Repository, https://github.com/sbusso/scrapework
